{"id":"pediatricsdiseases","entries":[{"name":"fragile X syndrome","term":"fragile X syndrome","identifiers":{"contentmine":"CM.pediatricsdiseases0","wikidata":"Q221472"}},{"name":"periventricular leukomalacia","term":"periventricular leukomalacia","identifiers":{"contentmine":"CM.pediatricsdiseases1","wikidata":"Q469490"}},{"name":"Williams-Beuren syndrome","term":"Williams-Beuren syndrome","identifiers":{"contentmine":"CM.pediatricsdiseases2","wikidata":"Q558077"}},{"name":"Prader-Willi syndrome","term":"Prader-Willi syndrome","identifiers":{"contentmine":"CM.pediatricsdiseases3","wikidata":"Q594013"}},{"name":"conduct disorder","term":"conduct disorder","identifiers":{"contentmine":"CM.pediatricsdiseases4","wikidata":"Q596474"}},{"name":"ileus","term":"ileus","identifiers":{"contentmine":"CM.pediatricsdiseases5","wikidata":"Q738153"}},{"name":"fetal erythroblastosis","term":"fetal erythroblastosis","identifiers":{"contentmine":"CM.pediatricsdiseases6","wikidata":"Q743545"}},{"name":"infant respiratory distress syndrome","term":"infant respiratory distress syndrome","identifiers":{"contentmine":"CM.pediatricsdiseases7","wikidata":"Q754348"}},{"name":"croup","term":"croup","identifiers":{"contentmine":"CM.pediatricsdiseases8","wikidata":"Q836356"}},{"name":"kernicterus","term":"kernicterus","identifiers":{"contentmine":"CM.pediatricsdiseases9","wikidata":"Q861845"}},{"name":"muscular dystrophy","term":"muscular dystrophy","identifiers":{"contentmine":"CM.pediatricsdiseases10","wikidata":"Q1137767"}},{"name":"twin-to-twin transfusion syndrome","term":"twin-to-twin transfusion syndrome","identifiers":{"contentmine":"CM.pediatricsdiseases11","wikidata":"Q1409160"}},{"name":"intussusception","term":"intussusception","identifiers":{"contentmine":"CM.pediatricsdiseases12","wikidata":"Q1424612"}},{"name":"intrauterine growth restriction","term":"intrauterine growth restriction","identifiers":{"contentmine":"CM.pediatricsdiseases13","wikidata":"Q1671598"}},{"name":"neonatal jaundice","term":"neonatal jaundice","identifiers":{"contentmine":"CM.pediatricsdiseases14","wikidata":"Q1755487"}},{"name":"meconium aspiration syndrome","term":"meconium aspiration syndrome","identifiers":{"contentmine":"CM.pediatricsdiseases15","wikidata":"Q1918881"}},{"name":"placental insufficiency","term":"placental insufficiency","identifiers":{"contentmine":"CM.pediatricsdiseases16","wikidata":"Q2099138"}},{"name":"congenital diaphragmatic hernia","term":"congenital diaphragmatic hernia","identifiers":{"contentmine":"CM.pediatricsdiseases17","wikidata":"Q2163245"}},{"name":"asphyxia neonatorum","term":"asphyxia neonatorum","identifiers":{"contentmine":"CM.pediatricsdiseases18","wikidata":"Q2694437"}},{"name":"anemia of prematurity","term":"anemia of prematurity","identifiers":{"contentmine":"CM.pediatricsdiseases19","wikidata":"Q4761649"}},{"name":"congenital cytomegalovirus infection","term":"congenital cytomegalovirus infection","identifiers":{"contentmine":"CM.pediatricsdiseases20","wikidata":"Q5160416"}},{"name":"pervasive developmental disorder","term":"pervasive developmental disorder","identifiers":{"contentmine":"CM.pediatricsdiseases21","wikidata":"Q6691991"}},{"name":"persistent fetal circulation syndrome","term":"persistent fetal circulation syndrome","identifiers":{"contentmine":"CM.pediatricsdiseases22","wikidata":"Q7170410"}},{"name":"placenta disease","term":"placenta disease","identifiers":{"contentmine":"CM.pediatricsdiseases23","wikidata":"Q7200296"}},{"name":"scleredema","term":"scleredema","identifiers":{"contentmine":"CM.pediatricsdiseases24","wikidata":"Q7434137"}},{"name":"subcutaneous fat necrosis of the newborn","term":"subcutaneous fat necrosis of the newborn","identifiers":{"contentmine":"CM.pediatricsdiseases25","wikidata":"Q7630991"}},{"name":"Tietz syndrome","term":"Tietz syndrome","identifiers":{"contentmine":"CM.pediatricsdiseases26","wikidata":"Q7801152"}},{"name":"transient neonatal diabetes mellitus","term":"transient neonatal diabetes mellitus","identifiers":{"contentmine":"CM.pediatricsdiseases27","wikidata":"Q7834286"}},{"name":"perinatal necrotizing enterocolitis","term":"perinatal necrotizing enterocolitis","identifiers":{"contentmine":"CM.pediatricsdiseases28","wikidata":"Q10859678"}}]}